Workbook

Sheet Assumptions
B2: Leep AI — Path to $50K Exit MRR
B3: Funnel and revenue model, reverse-engineered from the 31 Dec 2026 target
B5: HOW TO USE THIS MODEL
B6: Edit only the yellow cells. | F6: Blue text = an input you set. Black text = a formula, leave it alone.
B7: Green text | F7: means the cell pulls from another sheet.
B8: Start here: | F8: set Current MRR in C12. That single number drives the whole model.
B9: Then: | F9: set your Blended ACV in C16 and re-read the Funnel tab.
B10: After the Phase 3 pilot: | F10: replace the four benchmark conversion rates in C22:C25 with your measured numbers.
B12: THE GOAL
B13: Input | C13: Value | F13: Source / note
B14: Target exit MRR at 31 Dec 2026 | C14: 50000 | F14: Stated goal. Exit run-rate, not cumulative collected revenue.
B15: Current MRR <<< SET THIS FIRST | C15: 0 | F15: NOT PROVIDED. Assumed 0 = worst case. Ask Aaron.
B16: Incremental MRR required | C16: =MAX(0,C14-C15)
B17: Months remaining | C17: 4 | F17: Aug through Dec 2026.
B19: DEAL ECONOMICS
B20: Input | C20: Value | F20: Source / note
B21: Blended ACV per month | C21: 2500 | F21: Group tier. Market: $295-595 standalone, $750+ multi-location, $797-1,497 managed. $1,000+ requires a bundle.
B22: Annualised contract value | C22: =C21*12 | F22: Determines which win-rate benchmark band applies.
B23: Gross margin | C23: 0.65 | F23: Agency reseller margins run 50-80% gross, 65-80% net at steady state.
B24: Customers required | C24: =IF(C21<=0,0,ROUNDUP(C16/C21,0))
B25: Closes required per month | C25: =IF(C17<=0,0,C24/C17)
B27: FUNNEL CONVERSION RATES
B28: Replace column C with measured values after the Phase 3 pilot. Columns D and E are the published benchmarks.
B29: Stage | C29: Model | D29: Benchmark avg | E29: Top quartile | F29: Source
B30: Dial to live connect | C30: 0.2 | D30: 0.1 | E30: 0.22 | F30: Gong 300M+ calls: avg 5.4%, top quartile 13.3%. Generic data 8-12%; VERIFIED MOBILE DIRECT-DIAL 18-22%.
B31: Connect to meeting booked (set rate) | C31: 0.15 | D31: 0.046 | E31: 0.167 | F31: Gong 300M+ calls: average set rate 4.6%, top quartile 16.7%.
B32: Meeting to qualified opportunity | C32: 0.6 | D32: 0.5 | E32: 0.7 | F32: Assumption, not benchmarked. Signal-qualified pipeline should beat generic inbound.
B33: Qualified opportunity to close | C33: 0.3 | D33: 0.24 | E33: 0.35 | F33: $10-50K ACV band: 20-28%. Sub-$10K: 28-35%. Overall B2B avg 21%, SMB 31%.
B35: CAPACITY AND COST
B36: Input | C36: Value | F36: Source / note
B37: Number of callers | C37: 2 | F37: Aaron + Alec. Add a dedicated dialer to raise this.
B38: Selling days per month | C38: 20
B39: Sustainable dials per person per day | C39: 40 | F39: Realistic ceiling for someone who also closes and delivers. A full-time dialer does 80-100.
B40: Data cost per qualified prospect | C40: 2 | F40: Outscraper $3/1K, Apify $1.50/1K, Coresignal $49/mo, Apollo $49/mo. Verify in Phase 1.
B42: Sources: all benchmark figures are cited secondary research, not audited data. Treat as priors to test in Phase 3.
B43: Full citations in prospecting/03-deployment-plan-50k-mrr.md

Sheet Funnel
B2: Funnel Requirements
B3: Worked backwards from closes required. Compare the Model case against the Benchmark case.
B5: Stage | C5: Per month | D5: Per week | E5: Conv. rate | G5: Read this
B6: Closed customers | C6: =Assumptions!C25 | D6: =C6/4.33 | G6: The target, from the Assumptions tab.
B7: Qualified opportunities | C7: =IF(Assumptions!C33<=0,0,C6/Assumptions!C33) | D7: =C7/4.33 | E7: =Assumptions!C33 | G7: A real discovery call with a fit prospect.
B8: Meetings booked | C8: =IF(Assumptions!C32<=0,0,C7/Assumptions!C32) | D8: =C8/4.33 | E8: =Assumptions!C32
B9: Live connects | C9: =IF(Assumptions!C31<=0,0,C8/Assumptions!C31) | D9: =C9/4.33 | E9: =Assumptions!C31 | G9: Conversations with a decision maker.
B10: Dials required | C10: =IF(Assumptions!C30<=0,0,C9/Assumptions!C30) | D10: =C10/4.33 | E10: =Assumptions!C30
B12: CAPACITY CHECK
B13: Metric | C13: Value | G13: Read this
B14: Dials per day, whole team | C14: =IF(Assumptions!C38<=0,0,C10/Assumptions!C38)
B15: Dials per person per day | C15: =IF(Assumptions!C37<=0,0,C14/Assumptions!C37)
B16: Sustainable capacity per person per day | C16: =Assumptions!C39
B17: Verdict | C17: =IF(C15<=C16,"FEASIBLE","OVER CAPACITY") | G17: If OVER CAPACITY: raise ACV, add a caller, or extend the timeline. Trying harder will not close the gap.
B18: Extra callers needed | C18: =IF(Assumptions!C39<=0,0,MAX(0,ROUNDUP(C14/Assumptions!C39,0)-Assumptions!C37))
B20: ECONOMICS
B21: Metric | C21: Value | G21: Read this
B22: Monthly data cost | C22: =C10*Assumptions!C40 | G22: One prospect researched per dial attempted.
B23: Data cost per customer acquired | C23: =IF(C6<=0,0,C22/C6) | G23: Excludes labour, tools and platform fees. This is a floor, not a CAC.
B24: Gross profit at target MRR | C24: =Assumptions!C14*Assumptions!C23 | G24: $50K MRR is not $50K of profit. Before your own time and the tool stack.

Sheet Scenarios
B2: Scenarios
B3: Two independent views. Table 1: how ACV changes the customer count. Table 2: how the set rate changes the dial load.
B5: TABLE 1 — Price is the biggest lever
B6: Uses the incremental MRR gap and conversion rates from the Assumptions tab.
B7: Blended ACV/mo | C7: Annual ACV | D7: Customers | E7: Closes/mo | F7: Opps/mo | G7: Dials/mo | H7: Dials/person/day
B8: 1000 | C8: =B8*12 | D8: =ROUNDUP(Assumptions!$C$16/B8,0) | E8: =D8/Assumptions!$C$17 | F8: =E8/Assumptions!$C$33 | G8: =F8/Assumptions!$C$32/Assumptions!$C$31/Assumptions!$C$30 | H8: =G8/Assumptions!$C$38/Assumptions!$C$37 | I8: Below market for a bundle. Needs 50 customers.
B9: 1500 | C9: =B9*12 | D9: =ROUNDUP(Assumptions!$C$16/B9,0) | E9: =D9/Assumptions!$C$17 | F9: =E9/Assumptions!$C$33 | G9: =F9/Assumptions!$C$32/Assumptions!$C$31/Assumptions!$C$30 | H9: =G9/Assumptions!$C$38/Assumptions!$C$37
B10: 2000 | C10: =B10*12 | D10: =ROUNDUP(Assumptions!$C$16/B10,0) | E10: =D10/Assumptions!$C$17 | F10: =E10/Assumptions!$C$33 | G10: =F10/Assumptions!$C$32/Assumptions!$C$31/Assumptions!$C$30 | H10: =G10/Assumptions!$C$38/Assumptions!$C$37
B11: 2500 | C11: =B11*12 | D11: =ROUNDUP(Assumptions!$C$16/B11,0) | E11: =D11/Assumptions!$C$17 | F11: =E11/Assumptions!$C$33 | G11: =F11/Assumptions!$C$32/Assumptions!$C$31/Assumptions!$C$30 | H11: =G11/Assumptions!$C$38/Assumptions!$C$37 | I11: << Base case. Group tier, 3-8 location med spa.
B12: 3000 | C12: =B12*12 | D12: =ROUNDUP(Assumptions!$C$16/B12,0) | E12: =D12/Assumptions!$C$17 | F12: =E12/Assumptions!$C$33 | G12: =F12/Assumptions!$C$32/Assumptions!$C$31/Assumptions!$C$30 | H12: =G12/Assumptions!$C$38/Assumptions!$C$37
B13: 4000 | C13: =B13*12 | D13: =ROUNDUP(Assumptions!$C$16/B13,0) | E13: =D13/Assumptions!$C$17 | F13: =E13/Assumptions!$C$33 | G13: =F13/Assumptions!$C$32/Assumptions!$C$31/Assumptions!$C$30 | H13: =G13/Assumptions!$C$38/Assumptions!$C$37
B14: 5000 | C14: =B14*12 | D14: =ROUNDUP(Assumptions!$C$16/B14,0) | E14: =D14/Assumptions!$C$17 | F14: =E14/Assumptions!$C$33 | G14: =F14/Assumptions!$C$32/Assumptions!$C$31/Assumptions!$C$30 | H14: =G14/Assumptions!$C$38/Assumptions!$C$37
B17: TABLE 2 — The set rate is the riskiest assumption
B18: Holds ACV at the Assumptions value. Only the connect-to-meeting rate varies.
B19: Set rate | C19: Connects/mo | D19: Dials/mo | E19: Dials/day team | F19: Dials/person/day | G19: Verdict
B20: 0.046 | C20: =Funnel!$C$8/B20 | D20: =C20/Assumptions!$C$30 | E20: =D20/Assumptions!$C$38 | F20: =E20/Assumptions!$C$37 | G20: =IF(F20<=Assumptions!$C$39,"FEASIBLE","OVER CAPACITY") | I20: Gong average across 300M+ calls
B21: 0.07 | C21: =Funnel!$C$8/B21 | D21: =C21/Assumptions!$C$30 | E21: =D21/Assumptions!$C$38 | F21: =E21/Assumptions!$C$37 | G21: =IF(F21<=Assumptions!$C$39,"FEASIBLE","OVER CAPACITY") | I21: Modest lift over average
B22: 0.1 | C22: =Funnel!$C$8/B22 | D22: =C22/Assumptions!$C$30 | E22: =D22/Assumptions!$C$38 | F22: =E22/Assumptions!$C$37 | G22: =IF(F22<=Assumptions!$C$39,"FEASIBLE","OVER CAPACITY") | I22: Strong performance
B23: 0.15 | C23: =Funnel!$C$8/B23 | D23: =C23/Assumptions!$C$30 | E23: =D23/Assumptions!$C$38 | F23: =E23/Assumptions!$C$37 | G23: =IF(F23<=Assumptions!$C$39,"FEASIBLE","OVER CAPACITY") | I23: Model base case - near top quartile
B24: 0.167 | C24: =Funnel!$C$8/B24 | D24: =C24/Assumptions!$C$30 | E24: =D24/Assumptions!$C$38 | F24: =E24/Assumptions!$C$37 | G24: =IF(F24<=Assumptions!$C$39,"FEASIBLE","OVER CAPACITY") | I24: Gong top quartile
B27: The gap between the top and bottom rows of Table 2 is the single largest uncertainty in the plan.
B28: This is why the Phase 3 pilot exists. Measure it before committing to Phase 4 volume.

Sheet Pricing
B2: Price Architecture
B3: Market benchmarks and the package ladder. $1,000+/mo is a bundle price, never a single-product price.
B5: WHAT THE MARKET PAYS
B6: Offer | C6: Detail | D6: Low | E6: High | G6: Source
B7: Self-serve floor | C7: AIRA, Dialzara, Rosie, Voksha, Trillet, Smith.ai | D7: 25 | E7: 95 | G7: cloudtalk.io, voksha.com, trillet.ai
B8: SMB AI receptionist | C8: Standard agency-resold, single location | D8: 197 | E8: 597 | G8: ringlyn.com
B9: Agency resold per location | C9: Typical reseller price point | D9: 295 | E9: 595 | G9: trillet.ai white label pricing
B10: Multi-location practices | C10: Multi-site or high-value verticals | D10: 750 | E10: 1200 | G10: trillet.ai
B11: Managed, high-ticket vertical | C11: Managed outbound programmes | D11: 797 | E11: 1497 | G11: ringlyn.com
B13: THE PACKAGE LADDER
B14: Tier | C14: Composition | D14: Target/mo | E14: Annual | F14: Gross profit/yr | G14: Fits
B15: Entry | C15: One product, single location | D15: 625 | E15: =D15*12 | F15: =E15*Assumptions!$C$23 | G15: Referral and inbound only. Do not prospect for this
B16: Core | C16: Reactivation + voice AI, 1-2 locations | D16: 1500 | E16: =D16*12 | F16: =E16*Assumptions!$C$23 | G16: High-revenue single-location med spa
B17: Group | C17: Reactivation + voice + chat + hygiene, 3-8 loc | D17: 3250 | E17: =D17*12 | F17: =E17*Assumptions!$C$23 | G17: THE SPEARHEAD
B18: Value-event | C18: Group tier + diligence-grade data cleanup | D18: 5000 | E18: =D18*12 | F18: =E18*Assumptions!$C$23 | G18: Owner grooming for exit. EBITDA frame
B20: Setup and implementation fees are separate and do not count toward MRR. Charge them anyway to fund delivery capacity.
B22: CLOSE RATE AS A PRICE THERMOMETER
B23: Win rates fall as deal size rises. So an unusually high close rate is evidence of underpricing, not of skill.
B24: Observed close rate | C24: Diagnosis | G24: Action
B25: Above 40% | C25: Far above the $10-50K benchmark band of 20-28%. Underpriced | G25: Raise price 25-40% on the next 10 deals
B26: 30% to 40% | C26: Top quartile for the band. Price near optimal | G26: Hold. Optimise elsewhere
B27: 20% to 30% | C27: At benchmark | G27: Hold price, improve qualification
B28: Below 20% | C28: Read the loss reason, not the rate | G28: Price objection = price too high. No-decision = targeting wrong. Opposite fixes
B30: Note: the top of the stated 30-50% target is the warning line, not the goal. Aim at 30-35%.
B31: Source: optif.ai (939 companies), zenitdata.com, landbase.com, salesmotion.io

Sheet Data Sources
B2: Data Source Map
B3: Google Maps is the universe. Apollo and ZoomInfo are enrichment, never discovery.
B5: COVERAGE WARNING
B6: ZoomInfo covers approximately 20% of local service providers. Apollo covers less.
B7: Building top-of-funnel on Apollo silently discards roughly 80% of the addressable market.
B8: This explains the Apollo med spa result: ~500 records nationwide against 10,000+ actual locations.
B10: Signal | C10: Best source | D10: Cost | E10: Confidence | F10: Note
B11: Business universe by industry + geo | C11: Google Maps via Outscraper or Apify | D11: $1.50-3.00 / 1K | E11: High | F11: Outscraper simpler PAYG; Apify better custom extraction. Layer 1 of everything
B12: Receptionist job open 30+ days | C12: Coresignal API | D12: From $49/mo | E12: High | F12: NOT Apollo, NOT scraping Indeed. Coresignal is licensed and aggregates Indeed
B13: Reviews citing missed calls | C13: Google Maps review scrape | D13: Included in Layer 1 | E13: High | F13: Free rider on the universe scrape. Highest ROI signal in the stack
B14: Review velocity vs rating trend | C14: Google Maps review timestamps | D14: Included in Layer 1 | E14: High | F14: Computed, not scraped
B15: Google Business Profile thin | C15: Google Maps / Places | D15: Included in Layer 1 | E15: High
B16: Main line rings to a mobile | C16: Phone line-type lookup API | D16: Low per lookup | E16: High | F16: MANDATORY FILTER. Doubles connect rate from 8-12% to 18-22%
B17: Yelp response time over 1 hour | C17: NOT RELIABLY OBTAINABLE | D17: n/a | E17: Low | F17: Fusion API lacks the field, scraping prohibited. Use unanswered-reviews proxy instead
B18: Website tech, no chat widget | C18: Self-built HTTP fetch + DOM parse | D18: Near zero | E18: High | F18: Build it yourself, no vendor needed
B19: Incumbent software detection | C19: Tech detection, vendor TBD | D19: Unknown | E19: Medium | F19: OPEN RESEARCH ITEM. Do not assume BuiltWith or Wappalyzer covers Boulevard or Zenoti
B20: SEO rank #4-10 | C20: Rank tracking API by geo | D20: Scales with keywords | E20: Medium | F20: Cost scales with keyword x location. Budget carefully
B21: Paid ads running | C21: Meta Ad Library plus paid search tool | D21: Free to low | E21: High | F21: Meta Ad Library is free and a strong solvency proxy
B22: Permits, licences, fleet, DOT | C22: State and county public records | D22: Low cost, high labour | E22: Medium | F22: The non-Google solvency layer. Reserve for shortlist
B23: PE activity, grooming for exit | C23: Roll-up trackers, banker listings | D23: Medium | E23: Medium | F23: Strongest signal in the matrix. Partly manual
B24: Owner name and contact | C24: Apollo then manual | D24: From $49/mo | E24: Low-Med | F24: ~20% coverage. Plan for manual research on the rest
B26: ARCHITECTURAL WARNING
B27: Proxycurl shut down permanently on 4 July 2025 after LinkedIn's federal lawsuit. A pipeline built on a scraper that gets litigated out of existence dies overnight. Use licensed providers for anything load-bearing.
B29: Full citations in prospecting/03-deployment-plan-50k-mrr.md

Sheet Phases
B2: Phase Plan
B3: The real deadline is 1 October, not 31 December. Mid-market cycles run 30-90 days.
B5: Phase | C5: When | D5: Goal | E5: Exit criteria | F5: Primary risk
B6: Phase 0 | C6: This week | D6: Decide and unblock | E6: Current MRR known; Josh Astone and JJ Jardina in the repo; domain bought and warming | F6: Domain warmup is the hidden critical path. Delay here costs October
B7: Phase 1 | C7: Aug wk 1-2 | D7: Foundations, build nothing | E7: Compliance Gate 1 signed; price ladder set; every data source verified; 2,000-5,000 entity universe | F7: KILL CRITERION: cost per qualified prospect above $50 breaks the unit economics
B8: Phase 2 | C8: Aug wk 3-4 | D8: Build the engine | E8: 50 scored dossiers, 20 hand-verified, measured false-positive rate per signal | F8: Building signals that turn out not to be feedable. Yelp is the known case
B9: Phase 3 | C9: September | D9: Pilot and calibrate | E9: Real measured numbers for all four conversion rates; this model re-run with them | F9: Skipping this phase under time pressure. It is the one that de-risks everything
B10: Phase 4 | C10: October-Nov | D10: Full volume. BUILD FREEZES 1 OCT | E10: Pipeline sufficient that arithmetic, not hope, produces the target | F10: Engineering past 1 October steals hours from the close window
B11: Phase 5 | C11: Nov-Dec | D11: Close only | E11: $50K exit MRR at 31 December | F11: Delivery capacity becomes the binding constraint, not lead flow
B14: WHAT KILLS THIS — ranked by probability times damage
B15: Rank | C15: Risk | E15: Mitigation | F15: Phase
B16: 1 | C16: Set rate lands at benchmark, not top quartile | E16: Pilot before committing; raise ACV; add a dialer | F16: 3
B17: 2 | C17: Aaron and Alec become the bottleneck across four functions | E17: Dedicated dialer hired in Phase 1 | F17: 1
B18: 3 | C18: Building past 1 October eats the close window | E18: Hard build freeze, treated as a real date | F18: 4
B19: 4 | C19: Delivery capacity binds before lead flow does | E19: Charge setup fees to fund capacity | F19: 5
B20: 5 | C20: Signals turn out not to be scrapable | E20: Validate every source in Phase 1 | F20: 1
B21: 6 | C21: Compliance stops the SMS leg after the cadence is built on it | E21: Gate 1 before any build | F21: 1
B22: 7 | C22: Domain warmup started too late | E22: Buy and warm in Phase 0 | F22: 0
B23: 8 | C23: 80% contact coverage gap forces unsustainable manual research | E23: Maps as universe; budget manual time explicitly | F23: 1
B24: 9 | C24: Underpricing at $1,000 when the ICP supports $2,500+ | E24: Package ladder; close rate thermometer | F24: 1
B25: 10 | C25: Scoring model never calibrated, reference accounts never arrive | E25: Phase 0 blocker. Say so plainly if it slips | F25: 0
